<?xml version="1.0" encoding="UTF-8"?>
<objects serializationModel="Studio.02.02.00">
	<object class="AudioFile" id="{b3fb356e-8f1b-4c49-99be-14413ecfa365}">
		<property name="assetPath">
			<value>Music/Level Phase 3 Intro.wav</value>
		</property>
		<property name="isStreaming">
			<value>true</value>
		</property>
		<property name="frequencyInKHz">
			<value>44.0999985</value>
		</property>
		<property name="channelCount">
			<value>2</value>
		</property>
		<property name="length">
			<value>21.817777777777778</value>
		</property>
		<relationship name="masterAssetFolder">
			<destination>{5b554b81-63e2-420c-b307-706cea04aff1}</destination>
		</relationship>
	</object>
</objects>
